pyodv/__init__.py
pyodv/__main__.py
pyodv/__version__.py
pyodv/base.py
pyodv-0.0.6.dist-info/LICENSE
pyodv-0.0.6.dist-info/METADATA
pyodv-0.0.6.dist-info/WHEEL
pyodv-0.0.6.dist-info/entry_points.txt
pyodv-0.0.6.dist-info/top_level.txt
pyodv-0.0.6.dist-info/RECORD
