Metadata-Version: 2.1
Name: pyodv
Version: 0.0.6
Summary: Python package for reading ODV (Ocean Data Variables) files
Home-page: https://vliz-be-opsci.github.io/pyodv
Author: Rory Meyer
Author-email: rory.meyer@vliz.be
License: MIT
Classifier: License :: OSI Approved :: MIT License
Classifier: Programming Language :: Python
Classifier: Programming Language :: Python :: 3.8
License-File: LICENSE
Provides-Extra: dev
